{
  "id": "brainstorm-orphan-signal-style-reference",
  "name": "brainstorm-orphan-signal-style-reference",
  "title": "brainstorm: Orphan Signal 风格参考落地",
  "description": "围绕用户提供的 Orphan Signal 参考图，梳理 FableMap 可落地的视觉/交互/产品方案与 MVP 边界。",
  "status": "done",
  "dev_type": "frontend",
  "scope": "frontend-ui-brainstorm",
  "package": null,
  "priority": "P2",
  "creator": "lijin",
  "assignee": "lijin",
  "createdAt": "2026-05-11",
  "completedAt": "2026-05-11",
  "branch": null,
  "base_branch": "main",
  "worktree_path": null,
  "current_phase": 0,
  "next_action": [
    {
      "phase": 1,
      "action": "brainstorm"
    },
    {
      "phase": 2,
      "action": "research"
    },
    {
      "phase": 3,
      "action": "implement"
    },
    {
      "phase": 4,
      "action": "check"
    },
    {
      "phase": 5,
      "action": "update-spec"
    },
    {
      "phase": 6,
      "action": "record-session"
    }
  ],
  "commit": null,
  "pr_url": null,
  "subtasks": [],
  "children": [],
  "parent": null,
  "relatedFiles": [],
  "notes": "",
  "meta": {}
}